scrapy_ssdb_spider/__init__.py
scrapy_ssdb_spider/dupefilter.py
scrapy_ssdb_spider/queues.py
scrapy_ssdb_spider/scheduler.py
scrapy_ssdb_spider/spiders.py
scrapy_ssdb_spider/ssdb.py
scrapy_ssdb_spider/ssdb_default_settings.py
scrapy_ssdb_spider-0.1.1.dist-info/LICENSE
scrapy_ssdb_spider-0.1.1.dist-info/METADATA
scrapy_ssdb_spider-0.1.1.dist-info/WHEEL
scrapy_ssdb_spider-0.1.1.dist-info/top_level.txt
scrapy_ssdb_spider-0.1.1.dist-info/RECORD
