Metadata-Version: 2.1
Name: scrapy-ssdb-spider
Version: 0.1.1
Summary: Ssdb-based components for Scrapy.
Home-page: https://github.com/PickledFish/scrapy-ssdb-spider
Author: SuanCaiYu
Author-email: suancaiyu0413@gmail.com
License: MIT
Platform: UNKNOWN
Classifier: License :: OSI Approved :: MIT License
Classifier: Programming Language :: Python
Classifier: Programming Language :: Python :: 3
Classifier: Programming Language :: Python :: 3.6
Classifier: Programming Language :: Python :: Implementation :: CPython
Classifier: Programming Language :: Python :: Implementation :: PyPy
Requires-Python: >=3.6.0
Requires-Dist: scrapy
Requires-Dist: pyssdb
